auth0_avs/__init__.py
auth0_avs/frontend/dist/index.html
auth0_avs/frontend/dist/assets/index.33f1792e.js
auth0_avs/frontend/dist/assets/index.5223bee9.css
auth0_avs/frontend/dist/assets/index.7f67485c.js
streamlit_auth0_avs-0.0.3.dist-info/LICENSE
streamlit_auth0_avs-0.0.3.dist-info/METADATA
streamlit_auth0_avs-0.0.3.dist-info/WHEEL
streamlit_auth0_avs-0.0.3.dist-info/top_level.txt
streamlit_auth0_avs-0.0.3.dist-info/RECORD
