Metadata-Version: 2.1
Name: streamlit-auth0-avs
Version: 0.0.3
Home-page: 
Author: 
Author-email: 
Requires-Python: >=3.6
License-File: LICENSE
Requires-Dist: streamlit (>=0.63)
Requires-Dist: python-jose (==3.3.0)
